parquet_peek/__init__.py
parquet_peek/main.py
parquet_peek-0.1.5.dist-info/METADATA
parquet_peek-0.1.5.dist-info/WHEEL
parquet_peek-0.1.5.dist-info/entry_points.txt
parquet_peek-0.1.5.dist-info/RECORD
