Metadata-Version: 2.3
Name: parquet-peek
Version: 0.1.5
Summary: just a simple way to check parquet file contents
Author-email: wckdouglas <douglas@vant.ai>
Requires-Python: >=3.10
Requires-Dist: fsspec>=2024.9.0
Requires-Dist: gcsfs>=2024.9.0.post1
Requires-Dist: polars>=1.9.0
Requires-Dist: rich-click>=1.8.3
Requires-Dist: s3fs>=2024.9.0
